<?xml version="1.0"?>
<log>
<logentry
   revision="15002">
<author>nbenothman</author>
<date>2015-10-19T13:41:25.864876Z</date>
<paths>
<path
   kind="dir"
   copyfrom-path="/branches/v4.1"
   copyfrom-rev="15001"
   action="A">/tags/v4.1.6</path>
</paths>
<msg>NOJIRA Creating tag v4.1.6 from branch v4.1</msg>
</logentry>
<logentry
   revision="15003">
<author>distrelec_read</author>
<date>2015-10-19T13:44:32.724188Z</date>
<paths>
<path
   kind="file"
   action="M">/tags/v4.1.6/environment/.project</path>
<path
   kind="file"
   action="M">/tags/v4.1.6/environment/properties-config.xml</path>
</paths>
<msg>Correction of paths in environment for tag v4.1.6</msg>
</logentry>
<logentry
   revision="15030">
<author>nbenothman</author>
<date>2015-10-20T15:34:21.544435Z</date>
<paths>
<path
   kind="dir"
   copyfrom-path="/tags/v4.1.6"
   copyfrom-rev="15029"
   action="A">/branches/v4.1.6</path>
</paths>
<msg>NOJIRA  creating hot-fix branch from tag v4.1.6</msg>
</logentry>
<logentry
   revision="15032">
<author>rhaemmerli</author>
<date>2015-10-20T15:45:37.957601Z</date>
<paths>
<path
   kind="file"
   action="M">/branches/v4.1.6/hybris/bin/custom/distrelecB2Bstorefront/web/webroot/WEB-INF/terrific/modules/productlist/js/productlist.js</path>
<path
   kind="dir"
   action="M">/branches/v4.1.6</path>
<path
   kind="file"
   action="M">/branches/v4.1.6/hybris/bin/custom/distrelecB2Bstorefront/web/src/com/namics/distrelec/b2b/storefront/controllers/pages/CategoryPageController.java</path>
<path
   kind="dir"
   action="M">/branches/v4.1.6/environment</path>
<path
   kind="file"
   action="M">/branches/v4.1.6/hybris/bin/custom/distrelecB2Bstorefront/web/webroot/WEB-INF/views/desktop/pages/terrific/checkout/checkoutConfirmationPickupPage.jsp</path>
<path
   kind="dir"
   copyfrom-path="/branches/v4.1/environment/release-notes/v4.1.6.1"
   copyfrom-rev="15031"
   action="A">/branches/v4.1.6/environment/release-notes/v4.1.6.1</path>
<path
   kind="dir"
   action="M">/branches/v4.1.6/hybris/bin/custom/distrelecB2Bstorefront</path>
</paths>
<msg>NOJIRA: merge r15029, r15027, r15026, r15031 for hot-fix</msg>
</logentry>
<logentry
   revision="15033">
<author>nbenothman</author>
<date>2015-10-20T15:46:52.880128Z</date>
<paths>
<path
   kind="dir"
   copyfrom-path="/branches/v4.1.6"
   copyfrom-rev="15032"
   action="A">/tags/v4.1.6.1</path>
</paths>
<msg>NOJIRA creating tag v4.1.6.1 from branch v4.1.6</msg>
</logentry>
<logentry
   revision="15034">
<author>distrelec_read</author>
<date>2015-10-20T15:49:02.643622Z</date>
<paths>
<path
   kind="file"
   action="M">/tags/v4.1.6.1/environment/.project</path>
<path
   kind="file"
   action="M">/tags/v4.1.6.1/environment/properties-config.xml</path>
</paths>
<msg>Correction of paths in environment for tag v4.1.6.1</msg>
</logentry>
</log>
