<?xml version="1.0"?>
<log>
<logentry
   revision="9868">
<author>fbersani</author>
<date>2014-08-06T05:56:32.526271Z</date>
<paths>
<path
   kind="dir"
   action="A">/trunk/environment/release-notes/v3.0.m3</path>
<path
   kind="file"
   action="A">/trunk/environment/release-notes/v3.0.m3/src/release.properties</path>
<path
   kind="file"
   action="A">/trunk/environment/release-notes/v3.0.m3/src/installation.txt</path>
<path
   kind="dir"
   action="A">/trunk/environment/release-notes/v3.0.m3/src</path>
<path
   kind="file"
   action="A">/trunk/environment/release-notes/v3.0.m3/src/description.txt</path>
<path
   kind="file"
   action="A">/trunk/environment/release-notes/v3.0.m3/src/post_installation.txt</path>
</paths>
<msg>NOJIRA: release-notes for v3.0.m3</msg>
</logentry>
<logentry
   revision="9879">
<author>fbersani</author>
<date>2014-08-06T14:05:21.405186Z</date>
<paths>
<path
   kind="file"
   action="M">/trunk/environment/env-q-common/hybris/config/local.properties</path>
</paths>
<msg>DISTRELEC-4722 open orders activated on the platform for Atos Q system</msg>
</logentry>
<logentry
   revision="9882">
<author>fbersani</author>
<date>2014-08-06T15:58:18.361228Z</date>
<paths>
<path
   kind="file"
   action="M">/trunk/hybris/bin/custom/distrelecB2Bfacades/resources/distrelecB2Bfacades-spring.xml</path>
</paths>
<msg>DISTRELEC-4717 adding the missing dependency injection</msg>
</logentry>
<logentry
   revision="9885">
<author>fbersani</author>
<date>2014-08-07T05:53:42.400424Z</date>
<paths>
<path
   kind="dir"
   copyfrom-path="/trunk"
   copyfrom-rev="9884"
   action="A">/tags/v3.0.m4</path>
</paths>
<msg>NOJIRA deploy v3.0.m4</msg>
</logentry>
<logentry
   revision="9886">
<author>fbersani</author>
<date>2014-08-07T06:08:06.821379Z</date>
<paths>
<path
   kind="file"
   action="M">/tags/v3.0.m4/environment/properties-config.xml</path>
<path
   kind="file"
   action="M">/tags/v3.0.m4/environment/.project</path>
</paths>
<msg>NOJIRA Correction of paths in environment for tag v3.0.m4</msg>
</logentry>
</log>
